{
  "shortName": "EBB",
  "zone": "jp",
  "name": "EX Battle Boost",
  "bloc": {
    "nameFR": "Black & White Era",
    "nameEN": "Black & White Era"
  },
  "releaseDateFR": "2013-07-13 00:00:00",
  "releaseDateUS": null,
  "totalCards": 99,
  "secretCards": 6,
  "logo": "https://pokecardex.b-cdn.net/assets/images/logos_jp/EBB.png",
  "symbol": "https://pokecardex.b-cdn.net/assets/images/symboles_jp/EBB.png",
  "scrapedAt": "2026-05-09T13:53:42.667Z",
  "cards": [
    {
      "num": "001/093",
      "sort": 1,
      "nameFR": "Caratroc",
      "nameEN": "Shuckle",
      "nameDE": "Pottrott",
      "rarity": "Sans rareté",
      "illustrator": "MAHOU",
      "idPokedex": 213,
      "idCardmarket": 567391,
      "idTcgplayer": 603048,
      "cardmarketUrl": "https://www.cardmarket.com/fr/Pokemon/Products/Singles/EX-Battle-Boost/Shuckle",
      "image": "https://pokecardex-scans.b-cdn.net/sets_jp/EBB/1.jpg?class=hd",
      "versions": [
        "Standard",
        "Reverse",
        "Édition 1",
        "Édition 1 (Reverse)"
      ]
    },
    {
      "num": "002/093",
      "sort": 2,
      "nameFR": "Vipélierre",
      "nameEN": "Snivy",
      "nameDE": "Serpifeu",
      "rarity": "Sans rareté",
      "illustrator": "Aya Kusube",
      "idPokedex": 495,
      "idCardmarket": 567392,
      "idTcgplayer": 603050,
      "cardmarketUrl": "https://www.cardmarket.com/fr/Pokemon/Products/Singles/EX-Battle-Boost/Snivy-MG002",
      "image": "https://pokecardex-scans.b-cdn.net/sets_jp/EBB/2.jpg?class=hd",
      "versions": [
        "Standard",
        "Reverse",
        "Édition 1",
        "Édition 1 (Reverse)"
      ]
    },
    {
      "num": "003/093",
      "sort": 3,
      "nameFR": "Lianaja",
      "nameEN": "Servine",
      "nameDE": "Efoserp",
      "rarity": "Sans rareté",
      "illustrator": "Shigenori Negishi",
      "idPokedex": 496,
      "idCardmarket": 567393,
      "idTcgplayer": 603046,
      "cardmarketUrl": "https://www.cardmarket.com/fr/Pokemon/Products/Singles/EX-Battle-Boost/Servine-MG003",
      "image": "https://pokecardex-scans.b-cdn.net/sets_jp/EBB/3.jpg?class=hd",
      "versions": [
        "Standard",
        "Reverse",
        "Édition 1",
        "Édition 1 (Reverse)"
      ]
    },
    {
      "num": "004/093",
      "sort": 4,
      "nameFR": "Majaspic",
      "nameEN": "Serperior",
      "nameDE": "Serpiroyal",
      "rarity": "Sans rareté",
      "illustrator": "hatachu",
      "idPokedex": 497,
      "idCardmarket": 567394,
      "idTcgplayer": 603045,
      "cardmarketUrl": "https://www.cardmarket.com/fr/Pokemon/Products/Singles/EX-Battle-Boost/Serperior-MG004",
      "image": "https://pokecardex-scans.b-cdn.net/sets_jp/EBB/4.jpg?class=hd",
      "versions": [
        "Standard",
        "Reverse",
        "Édition 1",
        "Édition 1 (Reverse)"
      ]
    },
    {
      "num": "005/093",
      "sort": 5,
      "nameFR": "Larveyette",
      "nameEN": "Sewaddle",
      "nameDE": "Strawickl",
      "rarity": "Sans rareté",
      "illustrator": "Yuka Morii",
      "idPokedex": 540,
      "idCardmarket": 567395,
      "idTcgplayer": 603047,
      "cardmarketUrl": "https://www.cardmarket.com/fr/Pokemon/Products/Singles/EX-Battle-Boost/Sewaddle-MG005",
      "image": "https://pokecardex-scans.b-cdn.net/sets_jp/EBB/5.jpg?class=hd",
      "versions": [
        "Standard",
        "Reverse",
        "Édition 1",
        "Édition 1 (Reverse)"
      ]
    },
    {
      "num": "006/093",
      "sort": 6,
      "nameFR": "Couverdure",
      "nameEN": "Swadloon",
      "nameDE": "Folikon",
      "rarity": "Sans rareté",
      "illustrator": "sui",
      "idPokedex": 541,
      "idCardmarket": 567396,
      "idTcgplayer": 603055,
      "cardmarketUrl": "https://www.cardmarket.com/fr/Pokemon/Products/Singles/EX-Battle-Boost/Swadloon",
      "image": "https://pokecardex-scans.b-cdn.net/sets_jp/EBB/6.jpg?class=hd",
      "versions": [
        "Standard",
        "Reverse",
        "Édition 1",
        "Édition 1 (Reverse)"
      ]
    },
    {
      "num": "007/093",
      "sort": 7,
      "nameFR": "Manternel",
      "nameEN": "Leavanny",
      "nameDE": "Matrifol",
      "rarity": "Sans rareté",
      "illustrator": "match",
      "idPokedex": 542,
      "idCardmarket": 567397,
      "idTcgplayer": 603011,
      "cardmarketUrl": "https://www.cardmarket.com/fr/Pokemon/Products/Singles/EX-Battle-Boost/Leavanny",
      "image": "https://pokecardex-scans.b-cdn.net/sets_jp/EBB/7.jpg?class=hd",
      "versions": [
        "Standard",
        "Reverse",
        "Édition 1",
        "Édition 1 (Reverse)"
      ]
    },
    {
      "num": "008/093",
      "sort": 8,
      "nameFR": "Viridium",
      "nameEN": "Virizion",
      "nameDE": "Viridium",
      "rarity": "Sans rareté",
      "illustrator": "Atsuko Nishida",
      "idPokedex": 640,
      "idCardmarket": 567399,
      "idTcgplayer": 603065,
      "cardmarketUrl": "https://www.cardmarket.com/fr/Pokemon/Products/Singles/EX-Battle-Boost/Virizion",
      "image": "https://pokecardex-scans.b-cdn.net/sets_jp/EBB/8.jpg?class=hd",
      "versions": [
        "Standard",
        "Reverse",
        "Édition 1",
        "Édition 1 (Reverse)"
      ]
    },
    {
      "num": "009/093",
      "sort": 9,
      "nameFR": "Salamèche",
      "nameEN": "Charmander",
      "nameDE": "Glumanda",
      "rarity": "Sans rareté",
      "illustrator": "match",
      "idPokedex": 4,
      "idCardmarket": 567401,
      "idTcgplayer": 602980,
      "cardmarketUrl": "https://www.cardmarket.com/fr/Pokemon/Products/Singles/EX-Battle-Boost/Charmander",
      "image": "https://pokecardex-scans.b-cdn.net/sets_jp/EBB/9.jpg?class=hd",
      "versions": [
        "Standard",
        "Reverse",
        "Édition 1",
        "Édition 1 (Reverse)"
      ]
    },
    {
      "num": "010/093",
      "sort": 10,
      "nameFR": "Reptincel",
      "nameEN": "Charmeleon",
      "nameDE": "Glutexo",
      "rarity": "Sans rareté",
      "illustrator": "Akira Komayama",
      "idPokedex": 5,
      "idCardmarket": 567402,
      "idTcgplayer": 602981,
      "cardmarketUrl": "https://www.cardmarket.com/fr/Pokemon/Products/Singles/EX-Battle-Boost/Charmeleon",
      "image": "https://pokecardex-scans.b-cdn.net/sets_jp/EBB/10.jpg?class=hd",
      "versions": [
        "Standard",
        "Reverse",
        "Édition 1",
        "Édition 1 (Reverse)"
      ]
    },
    {
      "num": "011/093",
      "sort": 11,
      "nameFR": "Dracaufeu",
      "nameEN": "Charizard",
      "nameDE": "Glurak",
      "rarity": "Sans rareté",
      "illustrator": "TOKIYA",
      "idPokedex": 6,
      "idCardmarket": 567403,
      "idTcgplayer": 602979,
      "cardmarketUrl": "https://www.cardmarket.com/fr/Pokemon/Products/Singles/EX-Battle-Boost/Charizard",
      "image": "https://pokecardex-scans.b-cdn.net/sets_jp/EBB/11.jpg?class=hd",
      "versions": [
        "Standard",
        "Reverse",
        "Édition 1",
        "Édition 1 (Reverse)"
      ]
    },
    {
      "num": "012/093",
      "sort": 12,
      "nameFR": "Goupix",
      "nameEN": "Vulpix",
      "nameDE": "Vulpix",
      "rarity": "Sans rareté",
      "illustrator": "Masakazu Fukuda",
      "idPokedex": 37,
      "idCardmarket": 567404,
      "idTcgplayer": 603066,
      "cardmarketUrl": "https://www.cardmarket.com/fr/Pokemon/Products/Singles/EX-Battle-Boost/Vulpix",
      "image": "https://pokecardex-scans.b-cdn.net/sets_jp/EBB/12.jpg?class=hd",
      "versions": [
        "Standard",
        "Reverse",
        "Édition 1",
        "Édition 1 (Reverse)"
      ]
    },
    {
      "num": "013/093",
      "sort": 13,
      "nameFR": "Feunard",
      "nameEN": "Ninetales",
      "nameDE": "Vulnona",
      "rarity": "Sans rareté",
      "illustrator": "Satoshi Shirai",
      "idPokedex": 38,
      "idCardmarket": 567405,
      "idTcgplayer": 603022,
      "cardmarketUrl": "https://www.cardmarket.com/fr/Pokemon/Products/Singles/EX-Battle-Boost/Ninetales",
      "image": "https://pokecardex-scans.b-cdn.net/sets_jp/EBB/13.jpg?class=hd",
      "versions": [
        "Standard",
        "Reverse",
        "Édition 1",
        "Édition 1 (Reverse)"
      ]
    },
    {
      "num": "014/093",
      "sort": 14,
      "nameFR": "Sulfura",
      "nameEN": "Moltres",
      "nameDE": "Lavados",
      "rarity": "Sans rareté",
      "illustrator": "Mitsuhiro Arita",
      "idPokedex": 146,
      "idCardmarket": 567406,
      "idTcgplayer": 603020,
      "cardmarketUrl": "https://www.cardmarket.com/fr/Pokemon/Products/Singles/EX-Battle-Boost/Moltres",
      "image": "https://pokecardex-scans.b-cdn.net/sets_jp/EBB/14.jpg?class=hd",
      "versions": [
        "Standard",
        "Reverse",
        "Édition 1",
        "Édition 1 (Reverse)"
      ]
    },
    {
      "num": "015/093",
      "sort": 15,
      "nameFR": "Victini",
      "nameEN": "Victini",
      "nameDE": "Victini",
      "rarity": "Sans rareté",
      "illustrator": "Tomokazu Komiya",
      "idPokedex": 494,
      "idCardmarket": 567407,
      "idTcgplayer": 603063,
      "cardmarketUrl": "https://www.cardmarket.com/fr/Pokemon/Products/Singles/EX-Battle-Boost/Victini",
      "image": "https://pokecardex-scans.b-cdn.net/sets_jp/EBB/15.jpg?class=hd",
      "versions": [
        "Standard",
        "Reverse",
        "Édition 1",
        "Édition 1 (Reverse)"
      ]
    },
    {
      "num": "016/093",
      "sort": 16,
      "nameFR": "Victini-EX",
      "nameEN": "Victini-EX",
      "nameDE": "Victini-EX",
      "rarity": "Sans rareté",
      "illustrator": "Eske Yoshinob",
      "idPokedex": 494,
      "idCardmarket": 567408,
      "idTcgplayer": 603064,
      "cardmarketUrl": "https://www.cardmarket.com/fr/Pokemon/Products/Singles/EX-Battle-Boost/Victini-EX",
      "image": "https://pokecardex-scans.b-cdn.net/sets_jp/EBB/16.jpg?class=hd",
      "versions": [
        "Standard",
        "Édition 1"
      ]
    },
    {
      "num": "017/093",
      "sort": 17,
      "nameFR": "Gruikui",
      "nameEN": "Tepig",
      "nameDE": "Floink",
      "rarity": "Sans rareté",
      "illustrator": "Kanako Eo",
      "idPokedex": 498,
      "idCardmarket": 567409,
      "idTcgplayer": 603056,
      "cardmarketUrl": "https://www.cardmarket.com/fr/Pokemon/Products/Singles/EX-Battle-Boost/Tepig-MG017",
      "image": "https://pokecardex-scans.b-cdn.net/sets_jp/EBB/17.jpg?class=hd",
      "versions": [
        "Standard",
        "Reverse",
        "Édition 1",
        "Édition 1 (Reverse)"
      ]
    },
    {
      "num": "018/093",
      "sort": 18,
      "nameFR": "Grotichon",
      "nameEN": "Pignite",
      "nameDE": "Ferkokel",
      "rarity": "Sans rareté",
      "illustrator": "Kanako Eo",
      "idPokedex": 499,
      "idCardmarket": 567410,
      "idTcgplayer": 603026,
      "cardmarketUrl": "https://www.cardmarket.com/fr/Pokemon/Products/Singles/EX-Battle-Boost/Pignite",
      "image": "https://pokecardex-scans.b-cdn.net/sets_jp/EBB/18.jpg?class=hd",
      "versions": [
        "Standard",
        "Reverse",
        "Édition 1",
        "Édition 1 (Reverse)"
      ]
    },
    {
      "num": "019/093",
      "sort": 19,
      "nameFR": "Roitiflam",
      "nameEN": "Emboar",
      "nameDE": "Flambirex",
      "rarity": "Sans rareté",
      "illustrator": "Kanako Eo",
      "idPokedex": 500,
      "idCardmarket": 567411,
      "idTcgplayer": 602990,
      "cardmarketUrl": "https://www.cardmarket.com/fr/Pokemon/Products/Singles/EX-Battle-Boost/Emboar",
      "image": "https://pokecardex-scans.b-cdn.net/sets_jp/EBB/19.jpg?class=hd",
      "versions": [
        "Standard",
        "Reverse",
        "Édition 1",
        "Édition 1 (Reverse)"
      ]
    },
    {
      "num": "020/093",
      "sort": 20,
      "nameFR": "Reshiram",
      "nameEN": "Reshiram",
      "nameDE": "Reshiram",
      "rarity": "Sans rareté",
      "illustrator": "Aya Kusube",
      "idPokedex": 643,
      "idCardmarket": 567412,
      "idTcgplayer": 603038,
      "cardmarketUrl": "https://www.cardmarket.com/fr/Pokemon/Products/Singles/EX-Battle-Boost/Reshiram-V1",
      "image": "https://pokecardex-scans.b-cdn.net/sets_jp/EBB/20.jpg?class=hd",
      "versions": [
        "Standard",
        "Reverse",
        "Édition 1",
        "Édition 1 (Reverse)"
      ]
    },
    {
      "num": "021/093",
      "sort": 21,
      "nameFR": "Reshiram-EX",
      "nameEN": "Reshiram-EX",
      "nameDE": "Reshiram-EX",
      "rarity": "Sans rareté",
      "illustrator": "Shizurow",
      "idPokedex": 643,
      "idCardmarket": 567413,
      "idTcgplayer": 603040,
      "cardmarketUrl": "https://www.cardmarket.com/fr/Pokemon/Products/Singles/EX-Battle-Boost/Reshiram-EX",
      "image": "https://pokecardex-scans.b-cdn.net/sets_jp/EBB/21.jpg?class=hd",
      "versions": [
        "Standard",
        "Édition 1"
      ]
    },
    {
      "num": "022/093",
      "sort": 22,
      "nameFR": "Magicarpe",
      "nameEN": "Magikarp",
      "nameDE": "Karpador",
      "rarity": "Sans rareté",
      "illustrator": "Midori Harada",
      "idPokedex": 129,
      "idCardmarket": 567414,
      "idTcgplayer": 603014,
      "cardmarketUrl": "https://www.cardmarket.com/fr/Pokemon/Products/Singles/EX-Battle-Boost/Magikarp",
      "image": "https://pokecardex-scans.b-cdn.net/sets_jp/EBB/22.jpg?class=hd",
      "versions": [
        "Standard",
        "Reverse",
        "Édition 1",
        "Édition 1 (Reverse)"
      ]
    },
    {
      "num": "023/093",
      "sort": 23,
      "nameFR": "Léviator",
      "nameEN": "Gyarados",
      "nameDE": "Garados",
      "rarity": "Sans rareté",
      "illustrator": "hatachu",
      "idPokedex": 130,
      "idCardmarket": 567415,
      "idTcgplayer": 603002,
      "cardmarketUrl": "https://www.cardmarket.com/fr/Pokemon/Products/Singles/EX-Battle-Boost/Gyarados",
      "image": "https://pokecardex-scans.b-cdn.net/sets_jp/EBB/23.jpg?class=hd",
      "versions": [
        "Standard",
        "Reverse",
        "Édition 1",
        "Édition 1 (Reverse)"
      ]
    },
    {
      "num": "024/093",
      "sort": 24,
      "nameFR": "Artikodin",
      "nameEN": "Articuno",
      "nameDE": "Arktos",
      "rarity": "Sans rareté",
      "illustrator": "Kagemaru Himeno",
      "idPokedex": 144,
      "idCardmarket": 567416,
      "idTcgplayer": 602974,
      "cardmarketUrl": "https://www.cardmarket.com/fr/Pokemon/Products/Singles/EX-Battle-Boost/Articuno",
      "image": "https://pokecardex-scans.b-cdn.net/sets_jp/EBB/24.jpg?class=hd",
      "versions": [
        "Standard",
        "Reverse",
        "Édition 1",
        "Édition 1 (Reverse)"
      ]
    },
    {
      "num": "025/093",
      "sort": 25,
      "nameFR": "Tiplouf",
      "nameEN": "Piplup",
      "nameDE": "Plinfa",
      "rarity": "Sans rareté",
      "illustrator": "Mizue",
      "idPokedex": 393,
      "idCardmarket": 567417,
      "idTcgplayer": 603027,
      "cardmarketUrl": "https://www.cardmarket.com/fr/Pokemon/Products/Singles/EX-Battle-Boost/Piplup",
      "image": "https://pokecardex-scans.b-cdn.net/sets_jp/EBB/25.jpg?class=hd",
      "versions": [
        "Standard",
        "Reverse",
        "Édition 1",
        "Édition 1 (Reverse)"
      ]
    },
    {
      "num": "026/093",
      "sort": 26,
      "nameFR": "Prinplouf",
      "nameEN": "Prinplup",
      "nameDE": "Pliprin",
      "rarity": "Sans rareté",
      "illustrator": "Miki Tanaka",
      "idPokedex": 394,
      "idCardmarket": 567418,
      "idTcgplayer": 603035,
      "cardmarketUrl": "https://www.cardmarket.com/fr/Pokemon/Products/Singles/EX-Battle-Boost/Prinplup",
      "image": "https://pokecardex-scans.b-cdn.net/sets_jp/EBB/26.jpg?class=hd",
      "versions": [
        "Standard",
        "Reverse",
        "Édition 1",
        "Édition 1 (Reverse)"
      ]
    },
    {
      "num": "027/093",
      "sort": 27,
      "nameFR": "Pingoléon",
      "nameEN": "Empoleon",
      "nameDE": "Impoleon",
      "rarity": "Sans rareté",
      "illustrator": "kawayoo",
      "idPokedex": 395,
      "idCardmarket": 567419,
      "idTcgplayer": 602992,
      "cardmarketUrl": "https://www.cardmarket.com/fr/Pokemon/Products/Singles/EX-Battle-Boost/Empoleon",
      "image": "https://pokecardex-scans.b-cdn.net/sets_jp/EBB/27.jpg?class=hd",
      "versions": [
        "Standard",
        "Reverse",
        "Édition 1",
        "Édition 1 (Reverse)"
      ]
    },
    {
      "num": "028/093",
      "sort": 28,
      "nameFR": "Phione",
      "nameEN": "Phione",
      "nameDE": "Phione",
      "rarity": "Sans rareté",
      "illustrator": "kawayoo",
      "idPokedex": 489,
      "idCardmarket": 567420,
      "idTcgplayer": 603025,
      "cardmarketUrl": "https://www.cardmarket.com/fr/Pokemon/Products/Singles/EX-Battle-Boost/Phione",
      "image": "https://pokecardex-scans.b-cdn.net/sets_jp/EBB/28.jpg?class=hd",
      "versions": [
        "Standard",
        "Reverse",
        "Édition 1",
        "Édition 1 (Reverse)"
      ]
    },
    {
      "num": "029/093",
      "sort": 29,
      "nameFR": "Moustillon",
      "nameEN": "Oshawott",
      "nameDE": "Ottaro",
      "rarity": "Sans rareté",
      "illustrator": "Midori Harada",
      "idPokedex": 501,
      "idCardmarket": 567421,
      "idTcgplayer": 603023,
      "cardmarketUrl": "https://www.cardmarket.com/fr/Pokemon/Products/Singles/EX-Battle-Boost/Oshawott-EBB029",
      "image": "https://pokecardex-scans.b-cdn.net/sets_jp/EBB/29.jpg?class=hd",
      "versions": [
        "Standard",
        "Reverse",
        "Édition 1",
        "Édition 1 (Reverse)"
      ]
    },
    {
      "num": "030/093",
      "sort": 30,
      "nameFR": "Mateloutre",
      "nameEN": "Dewott",
      "nameDE": "Zwottronin",
      "rarity": "Sans rareté",
      "illustrator": "Mizue",
      "idPokedex": 502,
      "idCardmarket": 567422,
      "idTcgplayer": 602987,
      "cardmarketUrl": "https://www.cardmarket.com/fr/Pokemon/Products/Singles/EX-Battle-Boost/Dewott-EBB030",
      "image": "https://pokecardex-scans.b-cdn.net/sets_jp/EBB/30.jpg?class=hd",
      "versions": [
        "Standard",
        "Reverse",
        "Édition 1",
        "Édition 1 (Reverse)"
      ]
    },
    {
      "num": "031/093",
      "sort": 31,
      "nameFR": "Clamiral",
      "nameEN": "Samurott",
      "nameDE": "Admurai",
      "rarity": "Sans rareté",
      "illustrator": "Naoki Saito",
      "idPokedex": 503,
      "idCardmarket": 567423,
      "idTcgplayer": 603043,
      "cardmarketUrl": "https://www.cardmarket.com/fr/Pokemon/Products/Singles/EX-Battle-Boost/Samurott",
      "image": "https://pokecardex-scans.b-cdn.net/sets_jp/EBB/31.jpg?class=hd",
      "versions": [
        "Standard",
        "Reverse",
        "Édition 1",
        "Édition 1 (Reverse)"
      ]
    },
    {
      "num": "032/093",
      "sort": 32,
      "nameFR": "Tritonde",
      "nameEN": "Tympole",
      "nameDE": "Schallquap",
      "rarity": "Sans rareté",
      "illustrator": "Kyoko Umemoto",
      "idPokedex": 535,
      "idCardmarket": 567424,
      "idTcgplayer": 603062,
      "cardmarketUrl": "https://www.cardmarket.com/fr/Pokemon/Products/Singles/EX-Battle-Boost/Tympole",
      "image": "https://pokecardex-scans.b-cdn.net/sets_jp/EBB/32.jpg?class=hd",
      "versions": [
        "Standard",
        "Reverse",
        "Édition 1",
        "Édition 1 (Reverse)"
      ]
    },
    {
      "num": "033/093",
      "sort": 33,
      "nameFR": "Batracné",
      "nameEN": "Palpitoad",
      "nameDE": "Mebrana",
      "rarity": "Sans rareté",
      "illustrator": "Sachiko Adachi",
      "idPokedex": 536,
      "idCardmarket": 567425,
      "idTcgplayer": 603024,
      "cardmarketUrl": "https://www.cardmarket.com/fr/Pokemon/Products/Singles/EX-Battle-Boost/Palpitoad",
      "image": "https://pokecardex-scans.b-cdn.net/sets_jp/EBB/33.jpg?class=hd",
      "versions": [
        "Standard",
        "Reverse",
        "Édition 1",
        "Édition 1 (Reverse)"
      ]
    },
    {
      "num": "034/093",
      "sort": 34,
      "nameFR": "Crapustule",
      "nameEN": "Seismitoad",
      "nameDE": "Branawarz",
      "rarity": "Sans rareté",
      "illustrator": "Hajime Kusajima",
      "idPokedex": 537,
      "idCardmarket": 567426,
      "idTcgplayer": 603044,
      "cardmarketUrl": "https://www.cardmarket.com/fr/Pokemon/Products/Singles/EX-Battle-Boost/Seismitoad",
      "image": "https://pokecardex-scans.b-cdn.net/sets_jp/EBB/34.jpg?class=hd",
      "versions": [
        "Standard",
        "Reverse",
        "Édition 1",
        "Édition 1 (Reverse)"
      ]
    },
    {
      "num": "035/093",
      "sort": 35,
      "nameFR": "Kyurem",
      "nameEN": "Kyurem",
      "nameDE": "Kyurem",
      "rarity": "Sans rareté",
      "illustrator": "Midori Harada",
      "idPokedex": 646,
      "idCardmarket": 567427,
      "idTcgplayer": 603008,
      "cardmarketUrl": "https://www.cardmarket.com/fr/Pokemon/Products/Singles/EX-Battle-Boost/Kyurem",
      "image": "https://pokecardex-scans.b-cdn.net/sets_jp/EBB/35.jpg?class=hd",
      "versions": [
        "Standard",
        "Reverse",
        "Édition 1",
        "Édition 1 (Reverse)"
      ]
    },
    {
      "num": "036/093",
      "sort": 36,
      "nameFR": "Kyurem-EX",
      "nameEN": "Kyurem-EX",
      "nameDE": "Kyurem-EX",
      "rarity": "Sans rareté",
      "illustrator": "Shizurow",
      "idPokedex": 646,
      "idCardmarket": 567428,
      "idTcgplayer": 603009,
      "cardmarketUrl": "https://www.cardmarket.com/fr/Pokemon/Products/Singles/EX-Battle-Boost/Kyurem-EX",
      "image": "https://pokecardex-scans.b-cdn.net/sets_jp/EBB/36.jpg?class=hd",
      "versions": [
        "Standard",
        "Édition 1"
      ]
    },
    {
      "num": "037/093",
      "sort": 37,
      "nameFR": "Keldeo-EX",
      "nameEN": "Keldeo-EX",
      "nameDE": "Keldeo-EX",
      "rarity": "Sans rareté",
      "illustrator": "Toyste Beach",
      "idPokedex": 647,
      "idCardmarket": 567429,
      "idTcgplayer": 603006,
      "cardmarketUrl": "https://www.cardmarket.com/fr/Pokemon/Products/Singles/EX-Battle-Boost/Keldeo-EX",
      "image": "https://pokecardex-scans.b-cdn.net/sets_jp/EBB/37.jpg?class=hd",
      "versions": [
        "Standard",
        "Édition 1"
      ]
    },
    {
      "num": "038/093",
      "sort": 38,
      "nameFR": "Electhor",
      "nameEN": "Zapdos",
      "nameDE": "Zapdos",
      "rarity": "Sans rareté",
      "illustrator": "Kouki Saitou",
      "idPokedex": 145,
      "idCardmarket": 567430,
      "idTcgplayer": 603069,
      "cardmarketUrl": "https://www.cardmarket.com/fr/Pokemon/Products/Singles/EX-Battle-Boost/Zapdos",
      "image": "https://pokecardex-scans.b-cdn.net/sets_jp/EBB/38.jpg?class=hd",
      "versions": [
        "Standard",
        "Reverse",
        "Édition 1",
        "Édition 1 (Reverse)"
      ]
    },
    {
      "num": "039/093",
      "sort": 39,
      "nameFR": "Posipi",
      "nameEN": "Plusle",
      "nameDE": "Plusle",
      "rarity": "Sans rareté",
      "illustrator": "Kouki Saitou",
      "idPokedex": 311,
      "idCardmarket": 567431,
      "idTcgplayer": 603028,
      "cardmarketUrl": "https://www.cardmarket.com/fr/Pokemon/Products/Singles/EX-Battle-Boost/Plusle",
      "image": "https://pokecardex-scans.b-cdn.net/sets_jp/EBB/39.jpg?class=hd",
      "versions": [
        "Standard",
        "Reverse",
        "Édition 1",
        "Édition 1 (Reverse)"
      ]
    },
    {
      "num": "040/093",
      "sort": 40,
      "nameFR": "Negapi",
      "nameEN": "Minun",
      "nameDE": "Minun",
      "rarity": "Sans rareté",
      "illustrator": "Kouki Saitou",
      "idPokedex": 312,
      "idCardmarket": 567432,
      "idTcgplayer": 603019,
      "cardmarketUrl": "https://www.cardmarket.com/fr/Pokemon/Products/Singles/EX-Battle-Boost/Minun",
      "image": "https://pokecardex-scans.b-cdn.net/sets_jp/EBB/40.jpg?class=hd",
      "versions": [
        "Standard",
        "Reverse",
        "Édition 1",
        "Édition 1 (Reverse)"
      ]
    },
    {
      "num": "041/093",
      "sort": 41,
      "nameFR": "Emolga",
      "nameEN": "Emolga",
      "nameDE": "Emolga",
      "rarity": "Sans rareté",
      "illustrator": "Tomokazu Komiya",
      "idPokedex": 587,
      "idCardmarket": 567433,
      "idTcgplayer": 602991,
      "cardmarketUrl": "https://www.cardmarket.com/fr/Pokemon/Products/Singles/EX-Battle-Boost/Emolga",
      "image": "https://pokecardex-scans.b-cdn.net/sets_jp/EBB/41.jpg?class=hd",
      "versions": [
        "Standard",
        "Reverse",
        "Édition 1",
        "Édition 1 (Reverse)"
      ]
    },
    {
      "num": "042/093",
      "sort": 42,
      "nameFR": "Fulguris",
      "nameEN": "Thundurus",
      "nameDE": "Voltolos",
      "rarity": "Sans rareté",
      "illustrator": "Yukiko Baba",
      "idPokedex": 642,
      "idCardmarket": 567434,
      "idTcgplayer": 603058,
      "cardmarketUrl": "https://www.cardmarket.com/fr/Pokemon/Products/Singles/EX-Battle-Boost/Thundurus",
      "image": "https://pokecardex-scans.b-cdn.net/sets_jp/EBB/42.jpg?class=hd",
      "versions": [
        "Standard",
        "Reverse",
        "Édition 1",
        "Édition 1 (Reverse)"
      ]
    },
    {
      "num": "043/093",
      "sort": 43,
      "nameFR": "Zekrom",
      "nameEN": "Zekrom",
      "nameDE": "Zekrom",
      "rarity": "Sans rareté",
      "illustrator": "Kagemaru Himeno",
      "idPokedex": 644,
      "idCardmarket": 567435,
      "idTcgplayer": 603070,
      "cardmarketUrl": "https://www.cardmarket.com/fr/Pokemon/Products/Singles/EX-Battle-Boost/Zekrom-V1",
      "image": "https://pokecardex-scans.b-cdn.net/sets_jp/EBB/43.jpg?class=hd",
      "versions": [
        "Standard",
        "Reverse",
        "Édition 1",
        "Édition 1 (Reverse)"
      ]
    },
    {
      "num": "044/093",
      "sort": 44,
      "nameFR": "Zekrom-EX",
      "nameEN": "Zekrom-EX",
      "nameDE": "Zekrom-EX",
      "rarity": "Sans rareté",
      "illustrator": "Shizurow",
      "idPokedex": 644,
      "idCardmarket": 567436,
      "idTcgplayer": 603072,
      "cardmarketUrl": "https://www.cardmarket.com/fr/Pokemon/Products/Singles/EX-Battle-Boost/Zekrom-EX",
      "image": "https://pokecardex-scans.b-cdn.net/sets_jp/EBB/44.jpg?class=hd",
      "versions": [
        "Standard",
        "Édition 1"
      ]
    },
    {
      "num": "045/093",
      "sort": 45,
      "nameFR": "Mewtwo-EX",
      "nameEN": "Mewtwo-EX",
      "nameDE": "Mewtu-EX",
      "rarity": "Sans rareté",
      "illustrator": "Shizurow",
      "idPokedex": 150,
      "idCardmarket": 567437,
      "idTcgplayer": 603017,
      "cardmarketUrl": "https://www.cardmarket.com/fr/Pokemon/Products/Singles/EX-Battle-Boost/Mewtwo-EX",
      "image": "https://pokecardex-scans.b-cdn.net/sets_jp/EBB/45.jpg?class=hd",
      "versions": [
        "Standard",
        "Édition 1"
      ]
    },
    {
      "num": "046/093",
      "sort": 46,
      "nameFR": "Natu",
      "nameEN": "Natu",
      "nameDE": "Natu",
      "rarity": "Sans rareté",
      "illustrator": "Sanosuke Sakuma",
      "idPokedex": 177,
      "idCardmarket": 567438,
      "idTcgplayer": 603021,
      "cardmarketUrl": "https://www.cardmarket.com/fr/Pokemon/Products/Singles/EX-Battle-Boost/Natu",
      "image": "https://pokecardex-scans.b-cdn.net/sets_jp/EBB/46.jpg?class=hd",
      "versions": [
        "Standard",
        "Reverse",
        "Édition 1",
        "Édition 1 (Reverse)"
      ]
    },
    {
      "num": "047/093",
      "sort": 47,
      "nameFR": "Xatu",
      "nameEN": "Xatu",
      "nameDE": "Xatu",
      "rarity": "Sans rareté",
      "illustrator": "Kouki Saitou",
      "idPokedex": 178,
      "idCardmarket": 567439,
      "idTcgplayer": 603068,
      "cardmarketUrl": "https://www.cardmarket.com/fr/Pokemon/Products/Singles/EX-Battle-Boost/Xatu",
      "image": "https://pokecardex-scans.b-cdn.net/sets_jp/EBB/47.jpg?class=hd",
      "versions": [
        "Standard",
        "Reverse",
        "Édition 1",
        "Édition 1 (Reverse)"
      ]
    },
    {
      "num": "048/093",
      "sort": 48,
      "nameFR": "Tarsal",
      "nameEN": "Ralts",
      "nameDE": "Trasla",
      "rarity": "Sans rareté",
      "illustrator": "Naoyo Kimura",
      "idPokedex": 280,
      "idCardmarket": 567440,
      "idTcgplayer": 603036,
      "cardmarketUrl": "https://www.cardmarket.com/fr/Pokemon/Products/Singles/EX-Battle-Boost/Ralts",
      "image": "https://pokecardex-scans.b-cdn.net/sets_jp/EBB/48.jpg?class=hd",
      "versions": [
        "Standard",
        "Reverse",
        "Édition 1",
        "Édition 1 (Reverse)"
      ]
    },
    {
      "num": "049/093",
      "sort": 49,
      "nameFR": "Kirlia",
      "nameEN": "Kirlia",
      "nameDE": "Kirlia",
      "rarity": "Sans rareté",
      "illustrator": "Yukiko Baba",
      "idPokedex": 281,
      "idCardmarket": 567441,
      "idTcgplayer": 603007,
      "cardmarketUrl": "https://www.cardmarket.com/fr/Pokemon/Products/Singles/EX-Battle-Boost/Kirlia",
      "image": "https://pokecardex-scans.b-cdn.net/sets_jp/EBB/49.jpg?class=hd",
      "versions": [
        "Standard",
        "Reverse",
        "Édition 1",
        "Édition 1 (Reverse)"
      ]
    },
    {
      "num": "050/093",
      "sort": 50,
      "nameFR": "Cradopaud",
      "nameEN": "Croagunk",
      "nameDE": "Glibunkel",
      "rarity": "Sans rareté",
      "illustrator": "Sanosuke Sakuma",
      "idPokedex": 453,
      "idCardmarket": 567442,
      "idTcgplayer": 602984,
      "cardmarketUrl": "https://www.cardmarket.com/fr/Pokemon/Products/Singles/EX-Battle-Boost/Croagunk-EBB050",
      "image": "https://pokecardex-scans.b-cdn.net/sets_jp/EBB/50.jpg?class=hd",
      "versions": [
        "Standard",
        "Reverse",
        "Édition 1",
        "Édition 1 (Reverse)"
      ]
    },
    {
      "num": "051/093",
      "sort": 51,
      "nameFR": "Coatox",
      "nameEN": "Toxicroak",
      "nameDE": "Toxiquak",
      "rarity": "Sans rareté",
      "illustrator": "Naoki Saito",
      "idPokedex": 454,
      "idCardmarket": 567445,
      "idTcgplayer": 603060,
      "cardmarketUrl": "https://www.cardmarket.com/fr/Pokemon/Products/Singles/EX-Battle-Boost/Toxicroak",
      "image": "https://pokecardex-scans.b-cdn.net/sets_jp/EBB/51.jpg?class=hd",
      "versions": [
        "Standard",
        "Reverse",
        "Édition 1",
        "Édition 1 (Reverse)"
      ]
    },
    {
      "num": "052/093",
      "sort": 52,
      "nameFR": "Cryptéro",
      "nameEN": "Sigilyph",
      "nameDE": "Symvolara",
      "rarity": "Sans rareté",
      "illustrator": "Shigenori Negishi",
      "idPokedex": 561,
      "idCardmarket": 567446,
      "idTcgplayer": 603049,
      "cardmarketUrl": "https://www.cardmarket.com/fr/Pokemon/Products/Singles/EX-Battle-Boost/Sigilyph",
      "image": "https://pokecardex-scans.b-cdn.net/sets_jp/EBB/52.jpg?class=hd",
      "versions": [
        "Standard",
        "Reverse",
        "Édition 1",
        "Édition 1 (Reverse)"
      ]
    },
    {
      "num": "053/093",
      "sort": 53,
      "nameFR": "Miamiasme",
      "nameEN": "Trubbish",
      "nameDE": "Unratütox",
      "rarity": "Sans rareté",
      "illustrator": "kawayoo",
      "idPokedex": 568,
      "idCardmarket": 567447,
      "idTcgplayer": 603061,
      "cardmarketUrl": "https://www.cardmarket.com/fr/Pokemon/Products/Singles/EX-Battle-Boost/Trubbish",
      "image": "https://pokecardex-scans.b-cdn.net/sets_jp/EBB/53.jpg?class=hd",
      "versions": [
        "Standard",
        "Reverse",
        "Édition 1",
        "Édition 1 (Reverse)"
      ]
    },
    {
      "num": "054/093",
      "sort": 54,
      "nameFR": "Miasmax",
      "nameEN": "Garbodor",
      "nameDE": "Deponitox",
      "rarity": "Sans rareté",
      "illustrator": "Tomoaki Imakuni",
      "idPokedex": 569,
      "idCardmarket": 567448,
      "idTcgplayer": 602996,
      "cardmarketUrl": "https://www.cardmarket.com/fr/Pokemon/Products/Singles/EX-Battle-Boost/Garbodor",
      "image": "https://pokecardex-scans.b-cdn.net/sets_jp/EBB/54.jpg?class=hd",
      "versions": [
        "Standard",
        "Reverse",
        "Édition 1",
        "Édition 1 (Reverse)"
      ]
    },
    {
      "num": "055/093",
      "sort": 55,
      "nameFR": "Scrutella",
      "nameEN": "Gothita",
      "nameDE": "Mollimorba",
      "rarity": "Sans rareté",
      "illustrator": "TOKIYA",
      "idPokedex": 574,
      "idCardmarket": 567449,
      "idTcgplayer": 602999,
      "cardmarketUrl": "https://www.cardmarket.com/fr/Pokemon/Products/Singles/EX-Battle-Boost/Gothita",
      "image": "https://pokecardex-scans.b-cdn.net/sets_jp/EBB/55.jpg?class=hd",
      "versions": [
        "Standard",
        "Reverse",
        "Édition 1",
        "Édition 1 (Reverse)"
      ]
    },
    {
      "num": "056/093",
      "sort": 56,
      "nameFR": "Mesmérella",
      "nameEN": "Gothorita",
      "nameDE": "Hypnomorba",
      "rarity": "Sans rareté",
      "illustrator": "kirisAki",
      "idPokedex": 575,
      "idCardmarket": 567450,
      "idTcgplayer": 603001,
      "cardmarketUrl": "https://www.cardmarket.com/fr/Pokemon/Products/Singles/EX-Battle-Boost/Gothorita",
      "image": "https://pokecardex-scans.b-cdn.net/sets_jp/EBB/56.jpg?class=hd",
      "versions": [
        "Standard",
        "Reverse",
        "Édition 1",
        "Édition 1 (Reverse)"
      ]
    },
    {
      "num": "057/093",
      "sort": 57,
      "nameFR": "Sidérella",
      "nameEN": "Gothitelle",
      "nameDE": "Morbitesse",
      "rarity": "Sans rareté",
      "illustrator": "kawayoo",
      "idPokedex": 576,
      "idCardmarket": 567451,
      "idTcgplayer": 603000,
      "cardmarketUrl": "https://www.cardmarket.com/fr/Pokemon/Products/Singles/EX-Battle-Boost/Gothitelle",
      "image": "https://pokecardex-scans.b-cdn.net/sets_jp/EBB/57.jpg?class=hd",
      "versions": [
        "Standard",
        "Reverse",
        "Édition 1",
        "Édition 1 (Reverse)"
      ]
    },
    {
      "num": "058/093",
      "sort": 58,
      "nameFR": "Nucléos",
      "nameEN": "Solosis",
      "nameDE": "Monozyto",
      "rarity": "Sans rareté",
      "illustrator": "HiRON",
      "idPokedex": 577,
      "idCardmarket": 567452,
      "idTcgplayer": 603051,
      "cardmarketUrl": "https://www.cardmarket.com/fr/Pokemon/Products/Singles/EX-Battle-Boost/Solosis-EBB058",
      "image": "https://pokecardex-scans.b-cdn.net/sets_jp/EBB/58.jpg?class=hd",
      "versions": [
        "Standard",
        "Reverse",
        "Édition 1",
        "Édition 1 (Reverse)"
      ]
    },
    {
      "num": "059/093",
      "sort": 59,
      "nameFR": "Méios",
      "nameEN": "Duosion",
      "nameDE": "Mitodos",
      "rarity": "Sans rareté",
      "illustrator": "Suwama Chiaki",
      "idPokedex": 578,
      "idCardmarket": 567453,
      "idTcgplayer": 602989,
      "cardmarketUrl": "https://www.cardmarket.com/fr/Pokemon/Products/Singles/EX-Battle-Boost/Duosion",
      "image": "https://pokecardex-scans.b-cdn.net/sets_jp/EBB/59.jpg?class=hd",
      "versions": [
        "Standard",
        "Reverse",
        "Édition 1",
        "Édition 1 (Reverse)"
      ]
    },
    {
      "num": "060/093",
      "sort": 60,
      "nameFR": "Symbios",
      "nameEN": "Reuniclus",
      "nameDE": "Zytomega",
      "rarity": "Sans rareté",
      "illustrator": "Kyoko Umemoto",
      "idPokedex": 579,
      "idCardmarket": 567454,
      "idTcgplayer": 603041,
      "cardmarketUrl": "https://www.cardmarket.com/fr/Pokemon/Products/Singles/EX-Battle-Boost/Reuniclus",
      "image": "https://pokecardex-scans.b-cdn.net/sets_jp/EBB/60.jpg?class=hd",
      "versions": [
        "Standard",
        "Reverse",
        "Édition 1",
        "Édition 1 (Reverse)"
      ]
    },
    {
      "num": "061/093",
      "sort": 61,
      "nameFR": "Lugulabre-EX",
      "nameEN": "Chandelure-EX",
      "nameDE": "Skelabra-EX",
      "rarity": "Sans rareté",
      "illustrator": "Ryo Ueda",
      "idPokedex": 609,
      "idCardmarket": 567455,
      "idTcgplayer": 602978,
      "cardmarketUrl": "https://www.cardmarket.com/fr/Pokemon/Products/Singles/EX-Battle-Boost/Chandelure-EX",
      "image": "https://pokecardex-scans.b-cdn.net/sets_jp/EBB/61.jpg?class=hd",
      "versions": [
        "Standard",
        "Édition 1"
      ]
    },
    {
      "num": "062/093",
      "sort": 62,
      "nameFR": "Meloetta",
      "nameEN": "Meloetta",
      "nameDE": "Meloetta",
      "rarity": "Sans rareté",
      "illustrator": "kawayoo",
      "idPokedex": 648,
      "idCardmarket": 567456,
      "idTcgplayer": 603015,
      "cardmarketUrl": "https://www.cardmarket.com/fr/Pokemon/Products/Singles/EX-Battle-Boost/Meloetta-V1",
      "image": "https://pokecardex-scans.b-cdn.net/sets_jp/EBB/62.jpg?class=hd",
      "versions": [
        "Standard",
        "Reverse",
        "Édition 1",
        "Édition 1 (Reverse)"
      ]
    },
    {
      "num": "063/093",
      "sort": 63,
      "nameFR": "Riolu",
      "nameEN": "Riolu",
      "nameDE": "Riolu",
      "rarity": "Sans rareté",
      "illustrator": "Naoyo Kimura",
      "idPokedex": 447,
      "idCardmarket": 567457,
      "idTcgplayer": 603042,
      "cardmarketUrl": "https://www.cardmarket.com/fr/Pokemon/Products/Singles/EX-Battle-Boost/Riolu",
      "image": "https://pokecardex-scans.b-cdn.net/sets_jp/EBB/63.jpg?class=hd",
      "versions": [
        "Standard",
        "Reverse",
        "Édition 1",
        "Édition 1 (Reverse)"
      ]
    },
    {
      "num": "064/093",
      "sort": 64,
      "nameFR": "Lucario",
      "nameEN": "Lucario",
      "nameDE": "Lucario",
      "rarity": "Sans rareté",
      "illustrator": "MAHOU",
      "idPokedex": 448,
      "idCardmarket": 567458,
      "idTcgplayer": 603012,
      "cardmarketUrl": "https://www.cardmarket.com/fr/Pokemon/Products/Singles/EX-Battle-Boost/Lucario",
      "image": "https://pokecardex-scans.b-cdn.net/sets_jp/EBB/64.jpg?class=hd",
      "versions": [
        "Standard",
        "Reverse",
        "Édition 1",
        "Édition 1 (Reverse)"
      ]
    },
    {
      "num": "065/093",
      "sort": 65,
      "nameFR": "Gallame",
      "nameEN": "Gallade",
      "nameDE": "Galagladi",
      "rarity": "Sans rareté",
      "illustrator": "Hajime Kusajima",
      "idPokedex": 475,
      "idCardmarket": 567459,
      "idTcgplayer": 602995,
      "cardmarketUrl": "https://www.cardmarket.com/fr/Pokemon/Products/Singles/EX-Battle-Boost/Gallade",
      "image": "https://pokecardex-scans.b-cdn.net/sets_jp/EBB/65.jpg?class=hd",
      "versions": [
        "Standard",
        "Reverse",
        "Édition 1",
        "Édition 1 (Reverse)"
      ]
    },
    {
      "num": "066/093",
      "sort": 66,
      "nameFR": "Minotaupe-EX",
      "nameEN": "Excadrill-EX",
      "nameDE": "Stalobor-EX",
      "rarity": "Sans rareté",
      "illustrator": "Ryo Ueda",
      "idPokedex": 530,
      "idCardmarket": 567460,
      "idTcgplayer": 602993,
      "cardmarketUrl": "https://www.cardmarket.com/fr/Pokemon/Products/Singles/EX-Battle-Boost/Excadrill-EX",
      "image": "https://pokecardex-scans.b-cdn.net/sets_jp/EBB/66.jpg?class=hd",
      "versions": [
        "Standard",
        "Édition 1"
      ]
    },
    {
      "num": "067/093",
      "sort": 67,
      "nameFR": "Limonde",
      "nameEN": "Stunfisk",
      "nameDE": "Flunschlik",
      "rarity": "Sans rareté",
      "illustrator": "Yuka Morii",
      "idPokedex": 618,
      "idCardmarket": 567461,
      "idTcgplayer": 603053,
      "cardmarketUrl": "https://www.cardmarket.com/fr/Pokemon/Products/Singles/EX-Battle-Boost/Stunfisk",
      "image": "https://pokecardex-scans.b-cdn.net/sets_jp/EBB/67.jpg?class=hd",
      "versions": [
        "Standard",
        "Reverse",
        "Édition 1",
        "Édition 1 (Reverse)"
      ]
    },
    {
      "num": "068/093",
      "sort": 68,
      "nameFR": "Terrakium",
      "nameEN": "Terrakion",
      "nameDE": "Terrakium",
      "rarity": "Sans rareté",
      "illustrator": "Shigenori Negishi",
      "idPokedex": 639,
      "idCardmarket": 567462,
      "idTcgplayer": 603057,
      "cardmarketUrl": "https://www.cardmarket.com/fr/Pokemon/Products/Singles/EX-Battle-Boost/Terrakion",
      "image": "https://pokecardex-scans.b-cdn.net/sets_jp/EBB/68.jpg?class=hd",
      "versions": [
        "Standard",
        "Reverse",
        "Édition 1",
        "Édition 1 (Reverse)"
      ]
    },
    {
      "num": "069/093",
      "sort": 69,
      "nameFR": "Démétéros",
      "nameEN": "Landorus",
      "nameDE": "Demeteros",
      "rarity": "Sans rareté",
      "illustrator": "Midori Harada",
      "idPokedex": 645,
      "idCardmarket": 567463,
      "idTcgplayer": 603010,
      "cardmarketUrl": "https://www.cardmarket.com/fr/Pokemon/Products/Singles/EX-Battle-Boost/Landorus",
      "image": "https://pokecardex-scans.b-cdn.net/sets_jp/EBB/69.jpg?class=hd",
      "versions": [
        "Standard",
        "Reverse",
        "Édition 1",
        "Édition 1 (Reverse)"
      ]
    },
    {
      "num": "070/093",
      "sort": 70,
      "nameFR": "Meloetta",
      "nameEN": "Meloetta",
      "nameDE": "Meloetta",
      "rarity": "Sans rareté",
      "illustrator": "Mizue",
      "idPokedex": 648,
      "idCardmarket": 567464,
      "idTcgplayer": 603016,
      "cardmarketUrl": "https://www.cardmarket.com/fr/Pokemon/Products/Singles/EX-Battle-Boost/Meloetta-V2",
      "image": "https://pokecardex-scans.b-cdn.net/sets_jp/EBB/70.jpg?class=hd",
      "versions": [
        "Standard",
        "Reverse",
        "Édition 1",
        "Édition 1 (Reverse)"
      ]
    },
    {
      "num": "071/093",
      "sort": 71,
      "nameFR": "Spiritomb",
      "nameEN": "Spiritomb",
      "nameDE": "Kryppuk",
      "rarity": "Sans rareté",
      "illustrator": "Mitsuhiro Arita",
      "idPokedex": 442,
      "idCardmarket": 567465,
      "idTcgplayer": 603052,
      "cardmarketUrl": "https://www.cardmarket.com/fr/Pokemon/Products/Singles/EX-Battle-Boost/Spiritomb",
      "image": "https://pokecardex-scans.b-cdn.net/sets_jp/EBB/71.jpg?class=hd",
      "versions": [
        "Standard",
        "Reverse",
        "Édition 1",
        "Édition 1 (Reverse)"
      ]
    },
    {
      "num": "072/093",
      "sort": 72,
      "nameFR": "Darkrai-EX",
      "nameEN": "Darkrai-EX",
      "nameDE": "Darkrai-EX",
      "rarity": "Sans rareté",
      "illustrator": "Shizurow",
      "idPokedex": 491,
      "idCardmarket": 567466,
      "idTcgplayer": 602985,
      "cardmarketUrl": "https://www.cardmarket.com/fr/Pokemon/Products/Singles/EX-Battle-Boost/Darkrai-EX-EBB072",
      "image": "https://pokecardex-scans.b-cdn.net/sets_jp/EBB/72.jpg?class=hd",
      "versions": [
        "Standard",
        "Édition 1"
      ]
    },
    {
      "num": "073/093",
      "sort": 73,
      "nameFR": "Zorua",
      "nameEN": "Zorua",
      "nameDE": "Zorua",
      "rarity": "Sans rareté",
      "illustrator": "Atsuko Nishida",
      "idPokedex": 570,
      "idCardmarket": 567467,
      "idTcgplayer": 603074,
      "cardmarketUrl": "https://www.cardmarket.com/fr/Pokemon/Products/Singles/EX-Battle-Boost/Zorua",
      "image": "https://pokecardex-scans.b-cdn.net/sets_jp/EBB/73.jpg?class=hd",
      "versions": [
        "Standard",
        "Reverse",
        "Édition 1",
        "Édition 1 (Reverse)"
      ]
    },
    {
      "num": "074/093",
      "sort": 74,
      "nameFR": "Zoroark",
      "nameEN": "Zoroark",
      "nameDE": "Zoroark",
      "rarity": "Sans rareté",
      "illustrator": "match",
      "idPokedex": 571,
      "idCardmarket": 567468,
      "idTcgplayer": 603073,
      "cardmarketUrl": "https://www.cardmarket.com/fr/Pokemon/Products/Singles/EX-Battle-Boost/Zoroark",
      "image": "https://pokecardex-scans.b-cdn.net/sets_jp/EBB/74.jpg?class=hd",
      "versions": [
        "Standard",
        "Reverse",
        "Édition 1",
        "Édition 1 (Reverse)"
      ]
    },
    {
      "num": "075/093",
      "sort": 75,
      "nameFR": "Cobaltium",
      "nameEN": "Cobalion",
      "nameDE": "Kobalium",
      "rarity": "Sans rareté",
      "illustrator": "Sumiyoshi Kizuki",
      "idPokedex": 638,
      "idCardmarket": 567469,
      "idTcgplayer": 602983,
      "cardmarketUrl": "https://www.cardmarket.com/fr/Pokemon/Products/Singles/EX-Battle-Boost/Cobalion",
      "image": "https://pokecardex-scans.b-cdn.net/sets_jp/EBB/75.jpg?class=hd",
      "versions": [
        "Standard",
        "Reverse",
        "Édition 1",
        "Édition 1 (Reverse)"
      ]
    },
    {
      "num": "076/093",
      "sort": 76,
      "nameFR": "Altaria",
      "nameEN": "Altaria",
      "nameDE": "Altaria",
      "rarity": "Sans rareté",
      "illustrator": "Atsuko Nishida",
      "idPokedex": 334,
      "idCardmarket": 567470,
      "idTcgplayer": 602973,
      "cardmarketUrl": "https://www.cardmarket.com/fr/Pokemon/Products/Singles/EX-Battle-Boost/Altaria",
      "image": "https://pokecardex-scans.b-cdn.net/sets_jp/EBB/76.jpg?class=hd",
      "versions": [
        "Standard",
        "Reverse",
        "Édition 1",
        "Édition 1 (Reverse)"
      ]
    },
    {
      "num": "077/093",
      "sort": 77,
      "nameFR": "Rayquaza",
      "nameEN": "Rayquaza",
      "nameDE": "Rayquaza",
      "rarity": "Sans rareté",
      "illustrator": "Shin Nagasawa",
      "idPokedex": 384,
      "idCardmarket": 567471,
      "idTcgplayer": 603037,
      "cardmarketUrl": "https://www.cardmarket.com/fr/Pokemon/Products/Singles/EX-Battle-Boost/Rayquaza",
      "image": "https://pokecardex-scans.b-cdn.net/sets_jp/EBB/77.jpg?class=hd",
      "versions": [
        "Standard",
        "Reverse",
        "Édition 1",
        "Édition 1 (Reverse)"
      ]
    },
    {
      "num": "078/093",
      "sort": 78,
      "nameFR": "Griknot",
      "nameEN": "Gible",
      "nameDE": "Kaumalat",
      "rarity": "Sans rareté",
      "illustrator": "sui",
      "idPokedex": 443,
      "idCardmarket": 567472,
      "idTcgplayer": 602998,
      "cardmarketUrl": "https://www.cardmarket.com/fr/Pokemon/Products/Singles/EX-Battle-Boost/Gible",
      "image": "https://pokecardex-scans.b-cdn.net/sets_jp/EBB/78.jpg?class=hd",
      "versions": [
        "Standard",
        "Reverse",
        "Édition 1",
        "Édition 1 (Reverse)"
      ]
    },
    {
      "num": "079/093",
      "sort": 79,
      "nameFR": "Carmache",
      "nameEN": "Gabite",
      "nameDE": "Knarksel",
      "rarity": "Sans rareté",
      "illustrator": "Shigenori Negishi",
      "idPokedex": 444,
      "idCardmarket": 567473,
      "idTcgplayer": 602994,
      "cardmarketUrl": "https://www.cardmarket.com/fr/Pokemon/Products/Singles/EX-Battle-Boost/Gabite",
      "image": "https://pokecardex-scans.b-cdn.net/sets_jp/EBB/79.jpg?class=hd",
      "versions": [
        "Standard",
        "Reverse",
        "Édition 1",
        "Édition 1 (Reverse)"
      ]
    },
    {
      "num": "080/093",
      "sort": 80,
      "nameFR": "Carchacrok",
      "nameEN": "Garchomp",
      "nameDE": "Knakrack",
      "rarity": "Sans rareté",
      "illustrator": "Masakazu Fukuda",
      "idPokedex": 445,
      "idCardmarket": 567474,
      "idTcgplayer": 602997,
      "cardmarketUrl": "https://www.cardmarket.com/fr/Pokemon/Products/Singles/EX-Battle-Boost/Garchomp",
      "image": "https://pokecardex-scans.b-cdn.net/sets_jp/EBB/80.jpg?class=hd",
      "versions": [
        "Standard",
        "Reverse",
        "Édition 1",
        "Édition 1 (Reverse)"
      ]
    },
    {
      "num": "081/093",
      "sort": 81,
      "nameFR": "Solochi",
      "nameEN": "Deino",
      "nameDE": "Kapuno",
      "rarity": "Sans rareté",
      "illustrator": "Akira Komayama",
      "idPokedex": 633,
      "idCardmarket": 567475,
      "idTcgplayer": 602986,
      "cardmarketUrl": "https://www.cardmarket.com/fr/Pokemon/Products/Singles/EX-Battle-Boost/Deino",
      "image": "https://pokecardex-scans.b-cdn.net/sets_jp/EBB/81.jpg?class=hd",
      "versions": [
        "Standard",
        "Reverse",
        "Édition 1",
        "Édition 1 (Reverse)"
      ]
    },
    {
      "num": "082/093",
      "sort": 82,
      "nameFR": "Diamat",
      "nameEN": "Zweilous",
      "nameDE": "Duodino",
      "rarity": "Sans rareté",
      "illustrator": "Yukiko Baba",
      "idPokedex": 634,
      "idCardmarket": 567476,
      "idTcgplayer": 603075,
      "cardmarketUrl": "https://www.cardmarket.com/fr/Pokemon/Products/Singles/EX-Battle-Boost/Zweilous",
      "image": "https://pokecardex-scans.b-cdn.net/sets_jp/EBB/82.jpg?class=hd",
      "versions": [
        "Standard",
        "Reverse",
        "Édition 1",
        "Édition 1 (Reverse)"
      ]
    },
    {
      "num": "083/093",
      "sort": 83,
      "nameFR": "Trioxhydre",
      "nameEN": "Hydreigon",
      "nameDE": "Trikephalo",
      "rarity": "Sans rareté",
      "illustrator": "Tomokazu Komiya",
      "idPokedex": 635,
      "idCardmarket": 567477,
      "idTcgplayer": 603003,
      "cardmarketUrl": "https://www.cardmarket.com/fr/Pokemon/Products/Singles/EX-Battle-Boost/Hydreigon",
      "image": "https://pokecardex-scans.b-cdn.net/sets_jp/EBB/83.jpg?class=hd",
      "versions": [
        "Standard",
        "Reverse",
        "Édition 1",
        "Édition 1 (Reverse)"
      ]
    },
    {
      "num": "084/093",
      "sort": 84,
      "nameFR": "Kyurem Noir EX",
      "nameEN": "Black Kyurem-EX",
      "nameDE": "Schwarzes Kyurem-EX",
      "rarity": "Sans rareté",
      "illustrator": "Eske Yoshinob",
      "idPokedex": 646,
      "idCardmarket": 567478,
      "idTcgplayer": 603067,
      "cardmarketUrl": "https://www.cardmarket.com/fr/Pokemon/Products/Singles/EX-Battle-Boost/Black-Kyurem-EX",
      "image": "https://pokecardex-scans.b-cdn.net/sets_jp/EBB/84.jpg?class=hd",
      "versions": [
        "Standard",
        "Édition 1"
      ]
    },
    {
      "num": "085/093",
      "sort": 85,
      "nameFR": "Kyurem Blanc EX",
      "nameEN": "White Kyurem-EX",
      "nameDE": "Weißes Kyurem-EX",
      "rarity": "Sans rareté",
      "illustrator": "Eske Yoshinob",
      "idPokedex": 646,
      "idCardmarket": 567479,
      "idTcgplayer": 602975,
      "cardmarketUrl": "https://www.cardmarket.com/fr/Pokemon/Products/Singles/EX-Battle-Boost/White-Kyurem-EX-EBB085",
      "image": "https://pokecardex-scans.b-cdn.net/sets_jp/EBB/85.jpg?class=hd",
      "versions": [
        "Standard",
        "Édition 1"
      ]
    },
    {
      "num": "086/093",
      "sort": 86,
      "nameFR": "Lugia-EX",
      "nameEN": "Lugia-EX",
      "nameDE": "Lugia-EX",
      "rarity": "Sans rareté",
      "illustrator": "Toyste Beach",
      "idPokedex": 249,
      "idCardmarket": 567480,
      "idTcgplayer": 603013,
      "cardmarketUrl": "https://www.cardmarket.com/fr/Pokemon/Products/Singles/EX-Battle-Boost/Lugia-EX",
      "image": "https://pokecardex-scans.b-cdn.net/sets_jp/EBB/86.jpg?class=hd",
      "versions": [
        "Standard",
        "Édition 1"
      ]
    },
    {
      "num": "087/093",
      "sort": 87,
      "nameFR": "Tylton",
      "nameEN": "Swablu",
      "nameDE": "Wablu",
      "rarity": "Sans rareté",
      "illustrator": "Akira Komayama",
      "idPokedex": 333,
      "idCardmarket": 567481,
      "idTcgplayer": 603054,
      "cardmarketUrl": "https://www.cardmarket.com/fr/Pokemon/Products/Singles/EX-Battle-Boost/Swablu",
      "image": "https://pokecardex-scans.b-cdn.net/sets_jp/EBB/87.jpg?class=hd",
      "versions": [
        "Standard",
        "Reverse",
        "Édition 1",
        "Édition 1 (Reverse)"
      ]
    },
    {
      "num": "088/093",
      "sort": 88,
      "nameFR": "Chinchidou",
      "nameEN": "Minccino",
      "nameDE": "Picochilla",
      "rarity": "Sans rareté",
      "illustrator": "Midori Harada",
      "idPokedex": 572,
      "idCardmarket": 567482,
      "idTcgplayer": 603018,
      "cardmarketUrl": "https://www.cardmarket.com/fr/Pokemon/Products/Singles/EX-Battle-Boost/Minccino",
      "image": "https://pokecardex-scans.b-cdn.net/sets_jp/EBB/88.jpg?class=hd",
      "versions": [
        "Standard",
        "Reverse",
        "Édition 1",
        "Édition 1 (Reverse)"
      ]
    },
    {
      "num": "089/093",
      "sort": 89,
      "nameFR": "Pashmilla",
      "nameEN": "Cinccino",
      "nameDE": "Chillabell",
      "rarity": "Sans rareté",
      "illustrator": "Mitsuhiro Arita",
      "idPokedex": 573,
      "idCardmarket": 567483,
      "idTcgplayer": 602982,
      "cardmarketUrl": "https://www.cardmarket.com/fr/Pokemon/Products/Singles/EX-Battle-Boost/Cinccino",
      "image": "https://pokecardex-scans.b-cdn.net/sets_jp/EBB/89.jpg?class=hd",
      "versions": [
        "Standard",
        "Reverse",
        "Édition 1",
        "Édition 1 (Reverse)"
      ]
    },
    {
      "num": "090/093",
      "sort": 90,
      "nameFR": "Drakkarmin",
      "nameEN": "Druddigon",
      "nameDE": "Shardrago",
      "rarity": "Sans rareté",
      "illustrator": "match",
      "idPokedex": 621,
      "idCardmarket": 567484,
      "idTcgplayer": 602988,
      "cardmarketUrl": "https://www.cardmarket.com/fr/Pokemon/Products/Singles/EX-Battle-Boost/Druddigon",
      "image": "https://pokecardex-scans.b-cdn.net/sets_jp/EBB/90.jpg?class=hd",
      "versions": [
        "Standard",
        "Reverse",
        "Édition 1",
        "Édition 1 (Reverse)"
      ]
    },
    {
      "num": "091/093",
      "sort": 91,
      "nameFR": "Frison",
      "nameEN": "Bouffalant",
      "nameDE": "Bisofank",
      "rarity": "Sans rareté",
      "illustrator": "Sanosuke Sakuma",
      "idPokedex": 626,
      "idCardmarket": 567485,
      "idTcgplayer": 602976,
      "cardmarketUrl": "https://www.cardmarket.com/fr/Pokemon/Products/Singles/EX-Battle-Boost/Bouffalant",
      "image": "https://pokecardex-scans.b-cdn.net/sets_jp/EBB/91.jpg?class=hd",
      "versions": [
        "Standard",
        "Reverse",
        "Édition 1",
        "Édition 1 (Reverse)"
      ]
    },
    {
      "num": "092/093",
      "sort": 92,
      "nameFR": "Boréas",
      "nameEN": "Tornadus",
      "nameDE": "Boreos",
      "rarity": "Sans rareté",
      "illustrator": "Miki Tanaka",
      "idPokedex": 641,
      "idCardmarket": 567486,
      "idTcgplayer": 603059,
      "cardmarketUrl": "https://www.cardmarket.com/fr/Pokemon/Products/Singles/EX-Battle-Boost/Tornadus",
      "image": "https://pokecardex-scans.b-cdn.net/sets_jp/EBB/92.jpg?class=hd",
      "versions": [
        "Standard",
        "Reverse",
        "Édition 1",
        "Édition 1 (Reverse)"
      ]
    },
    {
      "num": "093/093",
      "sort": 93,
      "nameFR": "Spruce Keteleeria",
      "nameEN": "Cedric Juniper",
      "nameDE": "Cedric Juniper",
      "rarity": "Sans rareté",
      "illustrator": "Ken Sugimori",
      "idPokedex": null,
      "idCardmarket": 567487,
      "idTcgplayer": 602977,
      "cardmarketUrl": "https://www.cardmarket.com/fr/Pokemon/Products/Singles/EX-Battle-Boost/Cedric-Juniper",
      "image": "https://pokecardex-scans.b-cdn.net/sets_jp/EBB/93.jpg?class=hd",
      "versions": [
        "Standard",
        "Reverse",
        "Édition 1",
        "Édition 1 (Reverse)"
      ]
    },
    {
      "num": "094/093",
      "sort": 94,
      "nameFR": "Reshiram",
      "nameEN": "Reshiram",
      "nameDE": "Reshiram",
      "rarity": "Sans rareté",
      "illustrator": "5ban Graphics",
      "idPokedex": 643,
      "idCardmarket": 567488,
      "idTcgplayer": 603039,
      "cardmarketUrl": "https://www.cardmarket.com/fr/Pokemon/Products/Singles/EX-Battle-Boost/Reshiram-V2",
      "image": "https://pokecardex-scans.b-cdn.net/sets_jp/EBB/94.jpg?class=hd",
      "versions": [
        "Standard",
        "Édition 1"
      ]
    },
    {
      "num": "095/093",
      "sort": 95,
      "nameFR": "Zekrom",
      "nameEN": "Zekrom",
      "nameDE": "Zekrom",
      "rarity": "Sans rareté",
      "illustrator": "5ban Graphics",
      "idPokedex": 644,
      "idCardmarket": 567489,
      "idTcgplayer": 603071,
      "cardmarketUrl": "https://www.cardmarket.com/fr/Pokemon/Products/Singles/EX-Battle-Boost/Zekrom-V2",
      "image": "https://pokecardex-scans.b-cdn.net/sets_jp/EBB/95.jpg?class=hd",
      "versions": [
        "Standard",
        "Édition 1"
      ]
    },
    {
      "num": "096/093",
      "sort": 96,
      "nameFR": "Imakuni ?",
      "nameEN": "Imakuni?",
      "nameDE": "Imakuni?s Dodu",
      "rarity": "Sans rareté",
      "illustrator": "—",
      "idPokedex": null,
      "idCardmarket": 567490,
      "idTcgplayer": 603004,
      "cardmarketUrl": "https://www.cardmarket.com/fr/Pokemon/Products/Singles/EX-Battle-Boost/Imakuni",
      "image": "https://pokecardex-scans.b-cdn.net/sets_jp/EBB/96.jpg?class=hd",
      "versions": [
        "Standard",
        "Édition 1"
      ]
    },
    {
      "num": "097/093",
      "sort": 97,
      "nameFR": "Pokémon Enterprise",
      "nameEN": "Pokémon Enterprise",
      "nameDE": "Pokémon Enterprise",
      "rarity": "Sans rareté",
      "illustrator": "—",
      "idPokedex": null,
      "idCardmarket": 567491,
      "idTcgplayer": 603029,
      "cardmarketUrl": "https://www.cardmarket.com/fr/Pokemon/Products/Singles/EX-Battle-Boost/Pokemon-Enterprise-V1",
      "image": "https://pokecardex-scans.b-cdn.net/sets_jp/EBB/97.jpg?class=hd",
      "versions": [
        "Standard",
        "Édition 1"
      ]
    },
    {
      "num": "098/093",
      "sort": 98,
      "nameFR": "Pokémon Enterprise",
      "nameEN": "Pokémon Enterprise",
      "nameDE": "Pokémon Enterprise",
      "rarity": "Sans rareté",
      "illustrator": "—",
      "idPokedex": null,
      "idCardmarket": 567492,
      "idTcgplayer": 603031,
      "cardmarketUrl": "https://www.cardmarket.com/fr/Pokemon/Products/Singles/EX-Battle-Boost/Pokemon-Enterprise-V2",
      "image": "https://pokecardex-scans.b-cdn.net/sets_jp/EBB/98.jpg?class=hd",
      "versions": [
        "Standard",
        "Édition 1"
      ]
    },
    {
      "num": "099/093",
      "sort": 99,
      "nameFR": "Pokémon Enterprise",
      "nameEN": "Pokémon Enterprise",
      "nameDE": "Pokémon Enterprise",
      "rarity": "Sans rareté",
      "illustrator": "—",
      "idPokedex": null,
      "idCardmarket": 567493,
      "idTcgplayer": 603033,
      "cardmarketUrl": "https://www.cardmarket.com/fr/Pokemon/Products/Singles/EX-Battle-Boost/Pokemon-Enterprise-V3",
      "image": "https://pokecardex-scans.b-cdn.net/sets_jp/EBB/99.jpg?class=hd",
      "versions": [
        "Standard",
        "Édition 1"
      ]
    }
  ]
}